{"Beauty Salon": [{"english": "1. I need a haircut.", "italian": "Ho bisogno di tagliare i capelli.", "spanish": "Necesito un corte de pelo.", "german": "Ich brauche einen Haarschnitt."}, {"english": "2. Can I book an appointment?", "italian": "Posso prenotare un appuntamento?", "spanish": "\u00bfPuedo reservar una cita?", "german": "Kann ich einen Termin vereinbaren?"}, {"english": "3. She is getting a facial.", "italian": "Lei sta facendo un trattamento per il viso.", "spanish": "Ella est\u00e1 haci\u00e9ndose un facial.", "german": "Sie bekommt eine Gesichtsbehandlung."}, {"english": "4. How much does a manicure cost?", "italian": "Quanto costa una manicure?", "spanish": "\u00bfCu\u00e1nto cuesta una manicura?", "german": "Wie viel kostet eine Manik\u00fcre?"}, {"english": "5. Do you offer massage services?", "italian": "Offrite servizi di massaggio?", "spanish": "\u00bfOfrecen servicios de masaje?", "german": "Bieten Sie Massagedienste an?"}, {"english": "6. The salon is closed on Sundays.", "italian": "Il salone \u00e8 chiuso la domenica.", "spanish": "El sal\u00f3n est\u00e1 cerrado los domingos.", "german": "Das Salon ist sonntags geschlossen."}, {"english": "7. I want to dye my hair blonde.", "italian": "Voglio schiarire i capelli biondi.", "spanish": "Quiero te\u00f1irme el cabello de rubio.", "german": "Ich m\u00f6chte meine Haare blond f\u00e4rben."}, {"english": "8. The stylist is cutting her hair.", "italian": "Lo stilista sta tagliando i capelli di lei.", "spanish": "El estilista est\u00e1 cort\u00e1ndole el pelo.", "german": "Der Stylist schneidet ihr Haar."}, {"english": "9. I love the ambiance of this salon.", "italian": "Amo l'atmosfera di questo salone.", "spanish": "Me encanta el ambiente de este sal\u00f3n.", "german": "Ich liebe die Atmosph\u00e4re dieses Salons."}, {"english": "10. Can I get a pedicure and a manicure?", "italian": "Posso fare una pedicure e una manicure?", "spanish": "\u00bfPuedo hacerme una pedicura y una manicura?", "german": "Kann ich eine Pedik\u00fcre und eine Manik\u00fcre bekommen?"}, {"english": "11. She is applying makeup.", "italian": "Lei sta applicando il trucco.", "spanish": "Ella est\u00e1 aplic\u00e1ndose maquillaje.", "german": "Sie tr\u00e4gt Make-up auf."}, {"english": "12. Do you have any hair products for sale?", "italian": "Avete prodotti per capelli in vendita?", "spanish": "\u00bfTienen productos para el cabello a la venta?", "german": "Haben Sie Haarprodukte zum Verkauf?"}, {"english": "13. I want to try a new hairstyle.", "italian": "Voglio provare un nuovo taglio di capelli.", "spanish": "Quiero probar un nuevo peinado.", "german": "Ich m\u00f6chte eine neue Frisur ausprobieren."}, {"english": "14. The salon offers facials and massages.", "italian": "Il salone offre trattamenti per il viso e massaggi.", "spanish": "El sal\u00f3n ofrece faciales y masajes.", "german": "Der Salon bietet Gesichtsbehandlungen und Massagen an."}, {"english": "15. Could you blow dry my hair, please?", "italian": "Potresti asciugarmi i capelli, per favore?", "spanish": "\u00bfPodr\u00edas secarme el cabello, por favor?", "german": "K\u00f6nnten Sie bitte meine Haare f\u00f6hnen?"}, {"english": "16. She is getting a gel manicure.", "italian": "Lei sta facendo una manicure in gel.", "spanish": "Ella est\u00e1 haci\u00e9ndose una manicura en gel.", "german": "Sie bekommt eine Gel-Manik\u00fcre."}, {"english": "17. The salon uses organic products.", "italian": "Il salone utilizza prodotti biologici.", "spanish": "El sal\u00f3n utiliza productos org\u00e1nicos.", "german": "Der Salon verwendet Bio-Produkte."}, {"english": "18. I want to schedule a hair color appointment.", "italian": "Voglio prenotare un appuntamento per la colorazione dei capelli.", "spanish": "Quiero agendar una cita para te\u00f1irme el cabello.", "german": "Ich m\u00f6chte einen Termin zur Haarfarbe vereinbaren."}, {"english": "19. The stylist is blow drying her hair.", "italian": "Lo stilista sta asciugando i capelli di lei.", "spanish": "El estilista est\u00e1 sec\u00e1ndole el pelo.", "german": "Der Stylist f\u00f6hnt ihr Haar."}, {"english": "20. I need a trim to get rid of split ends.", "italian": "Ho bisogno di rifilare i capelli per eliminare le doppie punte.", "spanish": "Necesito un corte para eliminar las puntas abiertas.", "german": "Ich brauche einen Schnitt, um Spliss loszuwerden."}]}