{"City Life": [{"english": "1. I love the hustle and bustle of the city.", "italian": "Adoro il trambusto della citt\u00e0.", "spanish": "Me encanta el bullicio de la ciudad.", "german": "Ich liebe das Trubeln der Stadt."}, {"english": "2. The city never sleeps.", "italian": "La citt\u00e0 non dorme mai.", "spanish": "La ciudad nunca duerme.", "german": "Die Stadt schl\u00e4ft nie."}, {"english": "3. The skyscrapers create a stunning skyline.", "italian": "I grattacieli creano un panorama mozzafiato.", "spanish": "Los rascacielos crean un horizonte impresionante.", "german": "Die Wolkenkratzer schaffen eine atemberaubende Skyline."}, {"english": "4. Public transportation is convenient in the city.", "italian": "I trasporti pubblici sono comodi in citt\u00e0.", "spanish": "El transporte p\u00fablico es conveniente en la ciudad.", "german": "Der \u00f6ffentliche Nahverkehr ist bequem in der Stadt."}, {"english": "5. The city offers a wide range of cultural events.", "italian": "La citt\u00e0 offre una vasta gamma di eventi culturali.", "spanish": "La ciudad ofrece una amplia gama de eventos culturales.", "german": "Die Stadt bietet eine Vielzahl von kulturellen Veranstaltungen."}, {"english": "6. I enjoy exploring the city's diverse neighborhoods.", "italian": "Mi piace esplorare i quartieri diversi della citt\u00e0.", "spanish": "Disfruto explorando los diversos barrios de la ciudad.", "german": "Ich genie\u00dfe es, die verschiedenen Viertel der Stadt zu erkunden."}, {"english": "7. The cityscape is filled with vibrant colors.", "italian": "Il panorama urbano \u00e8 pieno di colori vivaci.", "spanish": "El paisaje urbano est\u00e1 lleno de colores vibrantes.", "german": "Die Stadtkulisse ist voller lebendiger Farben."}, {"english": "8. The city is known for its lively nightlife.", "italian": "La citt\u00e0 \u00e8 famosa per la sua vivace vita notturna.", "spanish": "La ciudad es conocida por su animada vida nocturna.", "german": "Die Stadt ist bekannt f\u00fcr ihr lebhaftes Nachtleben."}, {"english": "9. I enjoy walking along the busy streets.", "italian": "Mi piace camminare lungo le strade affollate.", "spanish": "Disfruto caminando por las calles concurridas.", "german": "Ich gehe gerne durch die belebten Stra\u00dfen."}, {"english": "10. The city offers a wide variety of culinary options.", "italian": "La citt\u00e0 offre una vasta scelta di opzioni culinarie.", "spanish": "La ciudad ofrece una amplia variedad de opciones culinarias.", "german": "Die Stadt bietet eine gro\u00dfe Auswahl an kulinarischen M\u00f6glichkeiten."}, {"english": "11. The city is a melting pot of different cultures.", "italian": "La citt\u00e0 \u00e8 un crogiolo di diverse culture.", "spanish": "La ciudad es un crisol de diferentes culturas.", "german": "Die Stadt ist ein Schmelztiegel verschiedener Kulturen."}, {"english": "12. The city's architecture is a blend of old and new.", "italian": "L'architettura della citt\u00e0 \u00e8 un mix di vecchio e nuovo.", "spanish": "La arquitectura de la ciudad es una mezcla de lo antiguo y lo nuevo.", "german": "Die Architektur der Stadt ist eine Mischung aus Alt und Neu."}, {"english": "13. City parks provide a peaceful escape from the busy streets.", "italian": "I parchi cittadini offrono una fuga tranquilla dalle strade affollate.", "spanish": "Los parques de la ciudad ofrecen un escape tranquilo de las calles concurridas.", "german": "Stadtparks bieten eine friedliche Flucht vor den belebten Stra\u00dfen."}, {"english": "14. The city offers a wide range of shopping opportunities.", "italian": "La citt\u00e0 offre una vasta gamma di opportunit\u00e0 di shopping.", "spanish": "La ciudad ofrece una amplia gama de oportunidades de compras.", "german": "Die Stadt bietet eine Vielzahl von Einkaufsm\u00f6glichkeiten."}, {"english": "15. City dwellers are always on the go.", "italian": "Gli abitanti della citt\u00e0 sono sempre in movimento.", "spanish": "Los habitantes de la ciudad siempre est\u00e1n en marcha.", "german": "Stadtbewohner sind immer unterwegs."}, {"english": "16. I enjoy the energy and fast pace of city life.", "italian": "Mi piace l'energia e il ritmo frenetico della vita cittadina.", "spanish": "Disfruto de la energ\u00eda y el ritmo r\u00e1pido de la vida en la ciudad.", "german": "Ich genie\u00dfe die Energie und das schnelle Tempo des Stadtlebens."}, {"english": "17. The city's public spaces are great for people-watching.", "italian": "Gli spazi pubblici della citt\u00e0 sono ottimi per osservare la gente.", "spanish": "Los espacios p\u00fablicos de la ciudad son ideales para observar a la gente.", "german": "Die \u00f6ffentlichen Pl\u00e4tze der Stadt sind ideal zum Leute beobachten."}, {"english": "18. City life can be both exciting and overwhelming.", "italian": "La vita in citt\u00e0 pu\u00f2 essere sia emozionante che travolgente.", "spanish": "La vida en la ciudad puede ser emocionante y abrumadora al mismo tiempo.", "german": "Das Stadtleben kann sowohl aufregend als auch \u00fcberw\u00e4ltigend sein."}, {"english": "19. The city has a vibrant street art scene.", "italian": "La citt\u00e0 ha una vivace scena di street art.", "spanish": "La ciudad tiene una vibrante escena de arte callejero.", "german": "Die Stadt hat eine lebendige Street-Art-Szene."}, {"english": "20. City dwellers are constantly connected through technology.", "italian": "Gli abitanti della citt\u00e0 sono costantemente connessi attraverso la tecnologia.", "spanish": "Los habitantes de la ciudad est\u00e1n constantemente conectados a trav\u00e9s de la tecnolog\u00eda.", "german": "Stadtbewohner sind st\u00e4ndig \u00fcber Technologie verbunden."}]}